systembridgeshared/__init__.py
systembridgeshared/_version.py
systembridgeshared/base.py
systembridgeshared/common.py
systembridgeshared/logger.py
systembridgeshared/settings.py
systembridgeshared-4.0.7.dist-info/LICENSE
systembridgeshared-4.0.7.dist-info/METADATA
systembridgeshared-4.0.7.dist-info/WHEEL
systembridgeshared-4.0.7.dist-info/top_level.txt
systembridgeshared-4.0.7.dist-info/RECORD
