Metadata-Version: 2.1
Name: systembridgeshared
Version: 4.0.7
Summary: System Bridge Shared
Home-page: https://github.com/timmo001/system-bridge-shared
Author: Aidan Timson (Timmo)
Author-email: aidan@timmo.dev
License: Apache-2.0
Keywords: system-bridge
Requires-Python: >=3.11
License-File: LICENSE
Requires-Dist: aiohttp==3.10.3
Requires-Dist: colorlog==6.8.2
Requires-Dist: cryptography==43.0.0
Requires-Dist: incremental>=24.7.2
Requires-Dist: systembridgemodels>=4.2.4
